adbkonnekt/README.MD
adbkonnekt/__init__.py
adbkonnekt/requirements.txt
adbkonnekt/thirdparty.json
adbkonnekt-0.14.dist-info/LICENSE.rst
adbkonnekt-0.14.dist-info/METADATA
adbkonnekt-0.14.dist-info/WHEEL
adbkonnekt-0.14.dist-info/top_level.txt
adbkonnekt-0.14.dist-info/RECORD
