Metadata-Version: 2.1
Name: adbkonnekt
Version: 0.14
Summary: automates ADB management in Windows, ensuring ADB listens to all TCP (no USB!) devices, handles configurations, and restarts if killed
Home-page: https://github.com/hansalemaos/adbkonnekt
Author: Johannes Fischer
Author-email: aulasparticularesdealemaosp@gmail.com
License: MIT
Keywords: android,adb
Classifier: Development Status :: 4 - Beta
Classifier: Programming Language :: Python :: 3 :: Only
Classifier: Programming Language :: Python :: 3.10
Classifier: Topic :: Software Development :: Libraries :: Python Modules
Classifier: Topic :: Utilities
License-File: LICENSE.rst
Requires-Dist: konfigleser
Requires-Dist: procciao
Requires-Dist: psutil
Requires-Dist: sharedbuiltinmutables
Requires-Dist: subprocess-alive
Requires-Dist: touchtouch
